torcontrol/__init__.py
torcontrol/errors.py
torcontrol/onion_builder.py
torcontrol/utils.py
torcontrol/async_connection/__init__.py
torcontrol/async_connection/async_connection.py
torcontrol/async_connection/protocol.py
torcontrol/base/__init__.py
torcontrol/base/classes.py
torcontrol/base/enums.py
torcontrol/events/__init__.py
torcontrol/events/event_dispatcher.py
torcontrol/events/events.py
torcontrol/protocol/__init__.py
torcontrol/protocol/request_io.py
torcontrol/protocol/response.py
torcontrol/protocol/response_decoder.py
torcontrol/protocol/response_io.py
torcontrol/sync_connection/__init__.py
torcontrol/sync_connection/socket.py
torcontrol-1.0.0.dist-info/LICENSE
torcontrol-1.0.0.dist-info/WHEEL
torcontrol-1.0.0.dist-info/METADATA
torcontrol-1.0.0.dist-info/RECORD
